slow_learner/__init__.py
slow_learner/cli.py
slow_learner/learnt_types.py
slow_learner/py.typed
slow_learner/subtyping.py
slow_learner/type_learner.py
slow_learner/typedef_generation.py
slow_learner/utils.py
slow_learner-0.1.3.dist-info/METADATA
slow_learner-0.1.3.dist-info/WHEEL
slow_learner-0.1.3.dist-info/entry_points.txt
slow_learner-0.1.3.dist-info/licenses/LICENSE.txt
slow_learner-0.1.3.dist-info/RECORD
