Metadata-Version: 2.1
Name: slow-learner
Version: 0.1.3
Summary: Python type inference from a stream of data
Project-URL: Homepage, https://nj-vs-vh.name/project/slow-learner
Project-URL: Repository, https://github.com/nj-vs-vh/slow-learner
Project-URL: Issues, https://github.com/nj-vs-vh/slow-learner/issues
Author-email: Igor Vaiman <gosha.vaiman@gmail.com>
License-File: LICENSE.txt
Classifier: Development Status :: 4 - Beta
Classifier: Environment :: Console
Classifier: License :: OSI Approved :: GNU Affero General Public License v3
Classifier: Operating System :: OS Independent
Classifier: Programming Language :: Python :: 3
Classifier: Topic :: File Formats :: JSON
Classifier: Typing :: Typed
Requires-Python: >=3.8
Requires-Dist: click~=8.1
Requires-Dist: tqdm>=4.0.0
